turkmarker/__init__.py
turkmarker/manage.py
turkmarker/aws/__init__.py
turkmarker/aws/mturk.py
turkmarker/aws/s3.py
turkmarker/data/error.html
turkmarker/data/index.html
turkmarker/data/protocol.html
turkmarker/data/protocol.md
turkmarker/data/template_face.png
turkmarker/data/template_face.xcf
turkmarker/data/template_landmarks.csv
turkmarker/data/static/DejaVuSans.ttf
turkmarker/data/static/IMG_20170602_101058653.jpg
turkmarker/data/static/base.css
turkmarker/data/static/base.js
turkmarker/data/static/check.js
turkmarker/data/static/config.json
turkmarker/data/static/display_image.jpg
turkmarker/data/static/example_btn.png
turkmarker/data/static/example_warning.png
turkmarker/data/static/glyphicons-halflings-regular.eot
turkmarker/data/static/glyphicons-halflings-regular.svg
turkmarker/data/static/glyphicons-halflings-regular.ttf
turkmarker/data/static/glyphicons-halflings-regular.woff
turkmarker/data/static/glyphicons-halflings-white.png
turkmarker/data/static/glyphicons-halflings.png
turkmarker/data/static/json2.js
turkmarker/data/static/submit_task_btn.png
turkmarker/utilities/__init__.py
turkmarker/utilities/base.py
turkmarker/utilities/generate.py
turkmarker-1.0.1.dev1.dist-info/DESCRIPTION.rst
turkmarker-1.0.1.dev1.dist-info/METADATA
turkmarker-1.0.1.dev1.dist-info/RECORD
turkmarker-1.0.1.dev1.dist-info/WHEEL
turkmarker-1.0.1.dev1.dist-info/entry_points.txt
turkmarker-1.0.1.dev1.dist-info/metadata.json
turkmarker-1.0.1.dev1.dist-info/top_level.txt
